apico/__init__.py
apico/abc.py
apico/monitor.py
apico/request.py
apico-1.1.0.dist-info/LICENSE
apico-1.1.0.dist-info/METADATA
apico-1.1.0.dist-info/WHEEL
apico-1.1.0.dist-info/top_level.txt
apico-1.1.0.dist-info/RECORD
