Metadata-Version: 2.1
Name: apico
Version: 1.1.0
Summary: Tool for monitoring changes in RESTful APIs quickly and easily
Home-page: https://github.com/itsmewulf/apico
Author: itsmewulf
Author-email: wulf.developer@gmail.com
License: UNKNOWN
Keywords: api-wrapper,http,request,api,monitor
Platform: UNKNOWN
Classifier: Programming Language :: Python :: 3
Classifier: License :: OSI Approved :: MIT License
Classifier: Operating System :: OS Independent
Requires-Python: >=3.9
